DESCRIPTION.rst
LICENSE.md
MANIFEST.in
README.rst
setup.py
bash/versionpro-completion.bash
versionpro/__init__.py
versionpro/_version.py
versionpro/about.py
versionpro/cli.py
versionpro/colormap.py
versionpro/colors.py
versionpro/config.py
versionpro/core.py
versionpro/dryrun.py
versionpro/help.py