Metadata-Version: 1.2
Name: versionpro
Version: 0.5.2
Summary: Version Managmement Utility for Python3 Projects
Home-page: https://github.com/fstab50/versionpro
Author: Blake Huber
Author-email: blakeca00@gmail.com
License: GPL-3.0
Keywords: CI/CD continuous integration continuous deployment version management
Platform: UNKNOWN
Classifier: Topic :: Software Development :: Libraries :: Python Modules
Classifier: Development Status :: 4 - Beta
Classifier: Programming Language :: Python :: 3.6
Classifier: Programming Language :: Python :: 3.7
Classifier: License :: OSI Approved :: GNU General Public License v3 (GPLv3)
Classifier: Operating System :: POSIX :: Linux
Requires-Python: >=3.6, <4
